myCalculatorPackage/__init__.py
myCalculatorPackage/division/__init__.py
myCalculatorPackage/division/divide.py
myCalculatorPackage/multiplication/__init__.py
myCalculatorPackage/multiplication/multiply.py
myCalculatorPackagexyz-0.0.2.dist-info/LICENSE.txt
myCalculatorPackagexyz-0.0.2.dist-info/METADATA
myCalculatorPackagexyz-0.0.2.dist-info/WHEEL
myCalculatorPackagexyz-0.0.2.dist-info/top_level.txt
myCalculatorPackagexyz-0.0.2.dist-info/RECORD
